MANIFEST.in
setup.py
django_current_request.egg-info/PKG-INFO
django_current_request.egg-info/SOURCES.txt
django_current_request.egg-info/dependency_links.txt
django_current_request.egg-info/top_level.txt
djangocurrentrequest/__init__.py
djangocurrentrequest/middleware.py
test/test_middleware.py