Metadata-Version: 1.0
Name: django-current-request
Version: 0.1
Summary: For that time when you need the request
Home-page: http://github.com/futurice/django-current-request
Author: Jussi Vaihia
Author-email: jussi.vaihia@futurice.com
License: BSD
Keywords: django current request
Platform: UNKNOWN
